{
    "omega-ruby-alpha-sapphire": [
        "bind",
        "snore",
        "helping-hand",
        "knock-off",
        "gastro-acid",
        "earth-power",
        "stealth-rock",
        "bug-bite",
        "after-you"
    ],
    "black-2-white-2": [
        "bind",
        "snore",
        "sleep-talk",
        "helping-hand",
        "knock-off",
        "gastro-acid",
        "earth-power",
        "stealth-rock",
        "bug-bite",
        "after-you"
    ],
    "heartgold-soulsilver": [
        "headbutt",
        "string-shot",
        "snore",
        "mud-slap",
        "rollout",
        "ancient-power",
        "helping-hand",
        "gastro-acid",
        "earth-power",
        "bug-bite"
    ],
    "firered-leafgreen": [
        "body-slam",
        "double-edge",
        "mimic",
        "rock-slide",
        "substitute"
    ],
    "emerald": [
        "body-slam",
        "double-edge",
        "mimic",
        "defense-curl",
        "rock-slide",
        "substitute",
        "snore",
        "mud-slap",
        "endure",
        "rollout",
        "swagger",
        "sleep-talk"
    ],
    "xd": [
        "body-slam",
        "double-edge",
        "mimic",
        "substitute",
        "swagger"
    ],
    "platinum": [
        "snore",
        "mud-slap",
        "rollout",
        "ancient-power",
        "helping-hand",
        "gastro-acid",
        "earth-power"
    ]
}