{
    "heartgold-soulsilver": [
        "headbutt",
        "super-fang",
        "snore",
        "mud-slap",
        "icy-wind",
        "rollout",
        "fury-cutter",
        "dive",
        "signal-beam",
        "block",
        "aqua-tail",
        "iron-head"
    ],
    "firered-leafgreen": [
        "body-slam",
        "double-edge",
        "mimic",
        "rock-slide",
        "substitute"
    ],
    "xd": [
        "body-slam",
        "double-edge",
        "mimic",
        "substitute",
        "icy-wind",
        "swagger"
    ],
    "emerald": [
        "body-slam",
        "double-edge",
        "mimic",
        "defense-curl",
        "rock-slide",
        "substitute",
        "snore",
        "mud-slap",
        "icy-wind",
        "endure",
        "rollout",
        "swagger",
        "sleep-talk"
    ],
    "omega-ruby-alpha-sapphire": [
        "super-fang",
        "snore",
        "icy-wind",
        "iron-tail",
        "signal-beam",
        "block",
        "water-pulse",
        "aqua-tail",
        "iron-head"
    ],
    "black-2-white-2": [
        "super-fang",
        "snore",
        "icy-wind",
        "sleep-talk",
        "iron-tail",
        "signal-beam",
        "block",
        "aqua-tail",
        "iron-head"
    ],
    "platinum": [
        "snore",
        "mud-slap",
        "icy-wind",
        "rollout",
        "fury-cutter",
        "dive",
        "signal-beam",
        "aqua-tail",
        "iron-head"
    ]
}