{
    "omega-ruby-alpha-sapphire": [
        "cut",
        "hyper-beam",
        "dig",
        "toxic",
        "psychic",
        "double-team",
        "dream-eater",
        "flash",
        "rest",
        "substitute",
        "protect",
        "swagger",
        "attract",
        "sleep-talk",
        "return",
        "frustration",
        "hidden-power",
        "rain-dance",
        "sunny-day",
        "psych-up",
        "shadow-ball",
        "torment",
        "facade",
        "taunt",
        "secret-power",
        "payback",
        "dark-pulse",
        "giga-impact",
        "round",
        "echoed-voice",
        "retaliate",
        "snarl",
        "confide"
    ],
    "x-y": [
        "cut",
        "hyper-beam",
        "dig",
        "toxic",
        "psychic",
        "double-team",
        "dream-eater",
        "flash",
        "rest",
        "substitute",
        "protect",
        "swagger",
        "attract",
        "sleep-talk",
        "return",
        "frustration",
        "hidden-power",
        "rain-dance",
        "sunny-day",
        "psych-up",
        "shadow-ball",
        "torment",
        "facade",
        "taunt",
        "payback",
        "dark-pulse",
        "giga-impact",
        "round",
        "echoed-voice",
        "retaliate",
        "snarl",
        "confide"
    ],
    "black-2-white-2": [
        "cut",
        "hyper-beam",
        "dig",
        "toxic",
        "psychic",
        "double-team",
        "dream-eater",
        "flash",
        "rest",
        "substitute",
        "protect",
        "swagger",
        "attract",
        "return",
        "frustration",
        "hidden-power",
        "rain-dance",
        "sunny-day",
        "psych-up",
        "shadow-ball",
        "torment",
        "facade",
        "taunt",
        "payback",
        "giga-impact",
        "round",
        "echoed-voice",
        "retaliate",
        "work-up",
        "snarl"
    ],
    "xd": [
        "cut",
        "hyper-beam",
        "dig",
        "toxic",
        "psychic",
        "double-team",
        "flash",
        "rest",
        "protect",
        "attract",
        "return",
        "frustration",
        "iron-tail",
        "hidden-power",
        "rain-dance",
        "sunny-day",
        "shadow-ball",
        "torment",
        "facade",
        "taunt",
        "snatch",
        "secret-power"
    ],
    "heartgold-soulsilver": [
        "cut",
        "hyper-beam",
        "dig",
        "toxic",
        "psychic",
        "double-team",
        "dream-eater",
        "flash",
        "rest",
        "substitute",
        "protect",
        "endure",
        "swagger",
        "attract",
        "sleep-talk",
        "return",
        "frustration",
        "iron-tail",
        "hidden-power",
        "rain-dance",
        "sunny-day",
        "psych-up",
        "shadow-ball",
        "torment",
        "facade",
        "taunt",
        "snatch",
        "secret-power",
        "natural-gift",
        "payback",
        "dark-pulse",
        "giga-impact",
        "captivate"
    ],
    "platinum": [
        "cut",
        "hyper-beam",
        "dig",
        "toxic",
        "psychic",
        "double-team",
        "dream-eater",
        "flash",
        "rest",
        "substitute",
        "protect",
        "endure",
        "swagger",
        "attract",
        "sleep-talk",
        "return",
        "frustration",
        "iron-tail",
        "hidden-power",
        "rain-dance",
        "sunny-day",
        "psych-up",
        "shadow-ball",
        "torment",
        "facade",
        "taunt",
        "snatch",
        "secret-power",
        "natural-gift",
        "payback",
        "dark-pulse",
        "giga-impact",
        "captivate"
    ],
    "diamond-pearl": [
        "cut",
        "hyper-beam",
        "dig",
        "toxic",
        "psychic",
        "double-team",
        "dream-eater",
        "flash",
        "rest",
        "substitute",
        "protect",
        "endure",
        "swagger",
        "attract",
        "sleep-talk",
        "return",
        "frustration",
        "iron-tail",
        "hidden-power",
        "rain-dance",
        "sunny-day",
        "psych-up",
        "shadow-ball",
        "torment",
        "facade",
        "taunt",
        "snatch",
        "secret-power",
        "natural-gift",
        "payback",
        "dark-pulse",
        "giga-impact",
        "captivate"
    ],
    "firered-leafgreen": [
        "cut",
        "hyper-beam",
        "dig",
        "toxic",
        "psychic",
        "double-team",
        "flash",
        "rest",
        "protect",
        "attract",
        "return",
        "frustration",
        "iron-tail",
        "hidden-power",
        "rain-dance",
        "sunny-day",
        "shadow-ball",
        "torment",
        "facade",
        "taunt",
        "snatch",
        "secret-power"
    ],
    "emerald": [
        "cut",
        "hyper-beam",
        "dig",
        "toxic",
        "psychic",
        "double-team",
        "flash",
        "rest",
        "protect",
        "attract",
        "return",
        "frustration",
        "iron-tail",
        "hidden-power",
        "rain-dance",
        "sunny-day",
        "shadow-ball",
        "torment",
        "facade",
        "taunt",
        "snatch",
        "secret-power"
    ],
    "ruby-sapphire": [
        "cut",
        "hyper-beam",
        "dig",
        "toxic",
        "psychic",
        "double-team",
        "flash",
        "rest",
        "protect",
        "attract",
        "return",
        "frustration",
        "iron-tail",
        "hidden-power",
        "rain-dance",
        "sunny-day",
        "shadow-ball",
        "torment",
        "facade",
        "taunt",
        "snatch",
        "secret-power"
    ],
    "colosseum": [
        "cut",
        "hyper-beam",
        "dig",
        "toxic",
        "psychic",
        "double-team",
        "flash",
        "rest",
        "protect",
        "attract",
        "return",
        "frustration",
        "iron-tail",
        "hidden-power",
        "rain-dance",
        "sunny-day",
        "shadow-ball",
        "torment",
        "facade",
        "taunt",
        "snatch",
        "secret-power"
    ],
    "black-white": [
        "cut",
        "hyper-beam",
        "dig",
        "toxic",
        "psychic",
        "double-team",
        "dream-eater",
        "flash",
        "rest",
        "substitute",
        "protect",
        "swagger",
        "attract",
        "return",
        "frustration",
        "hidden-power",
        "rain-dance",
        "sunny-day",
        "psych-up",
        "shadow-ball",
        "torment",
        "facade",
        "taunt",
        "payback",
        "giga-impact",
        "round",
        "echoed-voice",
        "retaliate",
        "work-up",
        "snarl"
    ],
    "crystal": [
        "cut",
        "headbutt",
        "hyper-beam",
        "toxic",
        "psychic",
        "double-team",
        "swift",
        "dream-eater",
        "flash",
        "rest",
        "nightmare",
        "snore",
        "curse",
        "protect",
        "mud-slap",
        "zap-cannon",
        "detect",
        "endure",
        "swagger",
        "attract",
        "sleep-talk",
        "return",
        "frustration",
        "iron-tail",
        "hidden-power",
        "rain-dance",
        "sunny-day",
        "psych-up",
        "shadow-ball"
    ],
    "gold-silver": [
        "cut",
        "headbutt",
        "hyper-beam",
        "toxic",
        "psychic",
        "double-team",
        "swift",
        "dream-eater",
        "flash",
        "rest",
        "nightmare",
        "snore",
        "curse",
        "protect",
        "mud-slap",
        "zap-cannon",
        "detect",
        "endure",
        "swagger",
        "attract",
        "sleep-talk",
        "return",
        "frustration",
        "iron-tail",
        "hidden-power",
        "rain-dance",
        "sunny-day",
        "psych-up",
        "shadow-ball"
    ],
    "ultra-sun-ultra-moon": [
        "hyper-beam",
        "toxic",
        "psychic",
        "double-team",
        "dream-eater",
        "rest",
        "substitute",
        "protect",
        "swagger",
        "attract",
        "sleep-talk",
        "return",
        "frustration",
        "hidden-power",
        "rain-dance",
        "sunny-day",
        "psych-up",
        "shadow-ball",
        "torment",
        "facade",
        "taunt",
        "payback",
        "dark-pulse",
        "giga-impact",
        "round",
        "echoed-voice",
        "work-up",
        "snarl",
        "confide"
    ],
    "sun-moon": [
        "hyper-beam",
        "toxic",
        "psychic",
        "double-team",
        "dream-eater",
        "rest",
        "substitute",
        "protect",
        "swagger",
        "attract",
        "sleep-talk",
        "return",
        "frustration",
        "hidden-power",
        "rain-dance",
        "sunny-day",
        "psych-up",
        "shadow-ball",
        "torment",
        "facade",
        "taunt",
        "payback",
        "dark-pulse",
        "giga-impact",
        "round",
        "echoed-voice",
        "work-up",
        "snarl",
        "confide"
    ]
}