{
    "ultra-sun-ultra-moon": [
        "swords-dance",
        "hyper-beam",
        "earthquake",
        "toxic",
        "double-team",
        "rest",
        "rock-slide",
        "substitute",
        "protect",
        "sandstorm",
        "false-swipe",
        "swagger",
        "attract",
        "sleep-talk",
        "return",
        "frustration",
        "hidden-power",
        "sunny-day",
        "facade",
        "brick-break",
        "rock-tomb",
        "aerial-ace",
        "rock-polish",
        "x-scissor",
        "giga-impact",
        "flash-cannon",
        "stone-edge",
        "smack-down",
        "round",
        "bulldoze",
        "confide",
        "brutal-swing"
    ],
    "sun-moon": [
        "swords-dance",
        "hyper-beam",
        "earthquake",
        "toxic",
        "double-team",
        "rest",
        "rock-slide",
        "substitute",
        "protect",
        "sandstorm",
        "false-swipe",
        "swagger",
        "attract",
        "sleep-talk",
        "return",
        "frustration",
        "hidden-power",
        "sunny-day",
        "facade",
        "brick-break",
        "rock-tomb",
        "aerial-ace",
        "rock-polish",
        "x-scissor",
        "giga-impact",
        "flash-cannon",
        "stone-edge",
        "smack-down",
        "round",
        "bulldoze",
        "confide",
        "brutal-swing"
    ],
    "black-2-white-2": [
        "swords-dance",
        "cut",
        "hyper-beam",
        "strength",
        "earthquake",
        "dig",
        "toxic",
        "double-team",
        "rest",
        "rock-slide",
        "substitute",
        "protect",
        "sandstorm",
        "false-swipe",
        "swagger",
        "attract",
        "return",
        "frustration",
        "hidden-power",
        "sunny-day",
        "rock-smash",
        "facade",
        "brick-break",
        "rock-tomb",
        "aerial-ace",
        "rock-polish",
        "x-scissor",
        "giga-impact",
        "flash-cannon",
        "stone-edge",
        "hone-claws",
        "smack-down",
        "round",
        "struggle-bug",
        "bulldoze"
    ],
    "black-white": [
        "swords-dance",
        "cut",
        "hyper-beam",
        "strength",
        "earthquake",
        "dig",
        "toxic",
        "double-team",
        "rest",
        "rock-slide",
        "substitute",
        "protect",
        "sandstorm",
        "false-swipe",
        "swagger",
        "attract",
        "return",
        "frustration",
        "hidden-power",
        "sunny-day",
        "rock-smash",
        "facade",
        "brick-break",
        "rock-tomb",
        "aerial-ace",
        "rock-polish",
        "x-scissor",
        "giga-impact",
        "flash-cannon",
        "stone-edge",
        "hone-claws",
        "smack-down",
        "round",
        "struggle-bug",
        "bulldoze"
    ],
    "omega-ruby-alpha-sapphire": [
        "swords-dance",
        "cut",
        "hyper-beam",
        "strength",
        "earthquake",
        "dig",
        "toxic",
        "double-team",
        "rest",
        "rock-slide",
        "substitute",
        "protect",
        "sandstorm",
        "false-swipe",
        "swagger",
        "attract",
        "sleep-talk",
        "return",
        "frustration",
        "hidden-power",
        "sunny-day",
        "rock-smash",
        "facade",
        "brick-break",
        "secret-power",
        "rock-tomb",
        "aerial-ace",
        "rock-polish",
        "x-scissor",
        "giga-impact",
        "flash-cannon",
        "stone-edge",
        "hone-claws",
        "smack-down",
        "round",
        "struggle-bug",
        "bulldoze",
        "confide"
    ],
    "x-y": [
        "swords-dance",
        "cut",
        "hyper-beam",
        "strength",
        "earthquake",
        "dig",
        "toxic",
        "double-team",
        "rest",
        "rock-slide",
        "substitute",
        "protect",
        "sandstorm",
        "false-swipe",
        "swagger",
        "attract",
        "sleep-talk",
        "return",
        "frustration",
        "hidden-power",
        "sunny-day",
        "rock-smash",
        "facade",
        "brick-break",
        "rock-tomb",
        "aerial-ace",
        "rock-polish",
        "x-scissor",
        "giga-impact",
        "flash-cannon",
        "stone-edge",
        "hone-claws",
        "smack-down",
        "round",
        "struggle-bug",
        "bulldoze",
        "confide"
    ],
    "heartgold-soulsilver": [
        "swords-dance",
        "cut",
        "hyper-beam",
        "strength",
        "earthquake",
        "dig",
        "toxic",
        "double-team",
        "rest",
        "rock-slide",
        "substitute",
        "protect",
        "sandstorm",
        "endure",
        "false-swipe",
        "swagger",
        "attract",
        "sleep-talk",
        "return",
        "frustration",
        "iron-tail",
        "hidden-power",
        "sunny-day",
        "rock-smash",
        "facade",
        "brick-break",
        "secret-power",
        "rock-tomb",
        "aerial-ace",
        "water-pulse",
        "natural-gift",
        "rock-polish",
        "x-scissor",
        "giga-impact",
        "flash-cannon",
        "stone-edge",
        "captivate",
        "stealth-rock"
    ],
    "platinum": [
        "swords-dance",
        "cut",
        "hyper-beam",
        "strength",
        "earthquake",
        "dig",
        "toxic",
        "double-team",
        "rest",
        "rock-slide",
        "substitute",
        "protect",
        "sandstorm",
        "endure",
        "false-swipe",
        "swagger",
        "attract",
        "sleep-talk",
        "return",
        "frustration",
        "iron-tail",
        "hidden-power",
        "sunny-day",
        "rock-smash",
        "facade",
        "brick-break",
        "secret-power",
        "rock-tomb",
        "aerial-ace",
        "water-pulse",
        "natural-gift",
        "rock-polish",
        "x-scissor",
        "giga-impact",
        "flash-cannon",
        "stone-edge",
        "captivate",
        "stealth-rock"
    ],
    "diamond-pearl": [
        "swords-dance",
        "cut",
        "hyper-beam",
        "strength",
        "earthquake",
        "dig",
        "toxic",
        "double-team",
        "rest",
        "rock-slide",
        "substitute",
        "protect",
        "sandstorm",
        "endure",
        "false-swipe",
        "swagger",
        "attract",
        "sleep-talk",
        "return",
        "frustration",
        "iron-tail",
        "hidden-power",
        "sunny-day",
        "rock-smash",
        "facade",
        "brick-break",
        "secret-power",
        "rock-tomb",
        "aerial-ace",
        "water-pulse",
        "natural-gift",
        "rock-polish",
        "x-scissor",
        "giga-impact",
        "flash-cannon",
        "stone-edge",
        "captivate",
        "stealth-rock"
    ],
    "xd": [
        "cut",
        "hyper-beam",
        "strength",
        "earthquake",
        "dig",
        "toxic",
        "double-team",
        "rest",
        "protect",
        "sandstorm",
        "attract",
        "return",
        "frustration",
        "iron-tail",
        "hidden-power",
        "sunny-day",
        "rock-smash",
        "facade",
        "brick-break",
        "secret-power",
        "rock-tomb",
        "aerial-ace",
        "water-pulse"
    ],
    "colosseum": [
        "cut",
        "hyper-beam",
        "strength",
        "earthquake",
        "dig",
        "toxic",
        "double-team",
        "rest",
        "protect",
        "sandstorm",
        "attract",
        "return",
        "frustration",
        "iron-tail",
        "hidden-power",
        "sunny-day",
        "rock-smash",
        "facade",
        "brick-break",
        "secret-power",
        "rock-tomb",
        "aerial-ace",
        "water-pulse"
    ],
    "firered-leafgreen": [
        "cut",
        "hyper-beam",
        "strength",
        "earthquake",
        "dig",
        "toxic",
        "double-team",
        "rest",
        "protect",
        "sandstorm",
        "attract",
        "return",
        "frustration",
        "iron-tail",
        "hidden-power",
        "sunny-day",
        "rock-smash",
        "facade",
        "brick-break",
        "secret-power",
        "rock-tomb",
        "aerial-ace",
        "water-pulse"
    ],
    "emerald": [
        "cut",
        "hyper-beam",
        "strength",
        "earthquake",
        "dig",
        "toxic",
        "double-team",
        "rest",
        "protect",
        "sandstorm",
        "attract",
        "return",
        "frustration",
        "iron-tail",
        "hidden-power",
        "sunny-day",
        "rock-smash",
        "facade",
        "brick-break",
        "secret-power",
        "rock-tomb",
        "aerial-ace",
        "water-pulse"
    ],
    "ruby-sapphire": [
        "cut",
        "hyper-beam",
        "strength",
        "earthquake",
        "dig",
        "toxic",
        "double-team",
        "rest",
        "protect",
        "sandstorm",
        "attract",
        "return",
        "frustration",
        "iron-tail",
        "hidden-power",
        "sunny-day",
        "rock-smash",
        "facade",
        "brick-break",
        "secret-power",
        "rock-tomb",
        "aerial-ace",
        "water-pulse"
    ]
}