{
    "sun-moon": [
        "ice-beam",
        "blizzard",
        "toxic",
        "psychic",
        "double-team",
        "dream-eater",
        "rest",
        "substitute",
        "thief",
        "protect",
        "swagger",
        "attract",
        "sleep-talk",
        "return",
        "frustration",
        "hidden-power",
        "rain-dance",
        "sunny-day",
        "psych-up",
        "shadow-ball",
        "torment",
        "will-o-wisp",
        "facade",
        "taunt",
        "calm-mind",
        "payback",
        "embargo",
        "fling",
        "dark-pulse",
        "trick-room",
        "charge-beam",
        "round",
        "confide",
        "infestation"
    ],
    "omega-ruby-alpha-sapphire": [
        "ice-beam",
        "blizzard",
        "toxic",
        "psychic",
        "double-team",
        "dream-eater",
        "flash",
        "rest",
        "substitute",
        "thief",
        "protect",
        "swagger",
        "attract",
        "sleep-talk",
        "return",
        "frustration",
        "hidden-power",
        "rain-dance",
        "sunny-day",
        "psych-up",
        "shadow-ball",
        "torment",
        "will-o-wisp",
        "facade",
        "taunt",
        "secret-power",
        "calm-mind",
        "payback",
        "embargo",
        "fling",
        "dark-pulse",
        "trick-room",
        "charge-beam",
        "round",
        "confide",
        "infestation"
    ],
    "x-y": [
        "ice-beam",
        "blizzard",
        "toxic",
        "psychic",
        "double-team",
        "dream-eater",
        "flash",
        "rest",
        "substitute",
        "thief",
        "protect",
        "swagger",
        "attract",
        "sleep-talk",
        "return",
        "frustration",
        "hidden-power",
        "rain-dance",
        "sunny-day",
        "psych-up",
        "shadow-ball",
        "torment",
        "will-o-wisp",
        "facade",
        "taunt",
        "calm-mind",
        "payback",
        "embargo",
        "fling",
        "dark-pulse",
        "trick-room",
        "charge-beam",
        "round",
        "confide",
        "infestation"
    ],
    "black-2-white-2": [
        "ice-beam",
        "blizzard",
        "toxic",
        "psychic",
        "double-team",
        "dream-eater",
        "flash",
        "rest",
        "substitute",
        "thief",
        "protect",
        "swagger",
        "attract",
        "return",
        "frustration",
        "hidden-power",
        "rain-dance",
        "sunny-day",
        "psych-up",
        "shadow-ball",
        "torment",
        "will-o-wisp",
        "facade",
        "taunt",
        "calm-mind",
        "payback",
        "embargo",
        "fling",
        "trick-room",
        "charge-beam",
        "telekinesis",
        "round"
    ],
    "xd": [
        "ice-beam",
        "blizzard",
        "toxic",
        "psychic",
        "double-team",
        "flash",
        "rest",
        "thief",
        "protect",
        "attract",
        "return",
        "frustration",
        "hidden-power",
        "rain-dance",
        "sunny-day",
        "shadow-ball",
        "torment",
        "facade",
        "taunt",
        "skill-swap",
        "snatch",
        "secret-power",
        "calm-mind"
    ],
    "colosseum": [
        "ice-beam",
        "blizzard",
        "toxic",
        "psychic",
        "double-team",
        "flash",
        "rest",
        "thief",
        "protect",
        "attract",
        "return",
        "frustration",
        "hidden-power",
        "rain-dance",
        "sunny-day",
        "shadow-ball",
        "torment",
        "facade",
        "taunt",
        "skill-swap",
        "snatch",
        "secret-power",
        "calm-mind"
    ],
    "black-white": [
        "ice-beam",
        "blizzard",
        "toxic",
        "psychic",
        "double-team",
        "dream-eater",
        "flash",
        "rest",
        "substitute",
        "thief",
        "protect",
        "swagger",
        "attract",
        "return",
        "frustration",
        "hidden-power",
        "rain-dance",
        "sunny-day",
        "psych-up",
        "shadow-ball",
        "torment",
        "will-o-wisp",
        "facade",
        "taunt",
        "calm-mind",
        "payback",
        "embargo",
        "fling",
        "trick-room",
        "charge-beam",
        "telekinesis",
        "round"
    ],
    "heartgold-soulsilver": [
        "ice-beam",
        "blizzard",
        "toxic",
        "psychic",
        "double-team",
        "dream-eater",
        "flash",
        "rest",
        "substitute",
        "thief",
        "protect",
        "endure",
        "swagger",
        "attract",
        "sleep-talk",
        "return",
        "frustration",
        "hidden-power",
        "rain-dance",
        "sunny-day",
        "psych-up",
        "shadow-ball",
        "torment",
        "will-o-wisp",
        "facade",
        "taunt",
        "skill-swap",
        "snatch",
        "secret-power",
        "calm-mind",
        "natural-gift",
        "payback",
        "embargo",
        "fling",
        "dark-pulse",
        "trick-room",
        "captivate",
        "charge-beam"
    ],
    "ultra-sun-ultra-moon": [
        "ice-beam",
        "blizzard",
        "toxic",
        "psychic",
        "double-team",
        "dream-eater",
        "rest",
        "substitute",
        "thief",
        "protect",
        "swagger",
        "attract",
        "sleep-talk",
        "return",
        "frustration",
        "hidden-power",
        "rain-dance",
        "sunny-day",
        "psych-up",
        "shadow-ball",
        "torment",
        "will-o-wisp",
        "facade",
        "taunt",
        "calm-mind",
        "payback",
        "embargo",
        "fling",
        "dark-pulse",
        "trick-room",
        "charge-beam",
        "round",
        "confide",
        "infestation"
    ],
    "platinum": [
        "ice-beam",
        "blizzard",
        "toxic",
        "psychic",
        "double-team",
        "dream-eater",
        "flash",
        "rest",
        "substitute",
        "thief",
        "protect",
        "endure",
        "swagger",
        "attract",
        "sleep-talk",
        "return",
        "frustration",
        "hidden-power",
        "rain-dance",
        "sunny-day",
        "psych-up",
        "shadow-ball",
        "torment",
        "will-o-wisp",
        "facade",
        "taunt",
        "skill-swap",
        "snatch",
        "secret-power",
        "calm-mind",
        "natural-gift",
        "payback",
        "embargo",
        "fling",
        "dark-pulse",
        "trick-room",
        "captivate",
        "charge-beam"
    ],
    "diamond-pearl": [
        "ice-beam",
        "blizzard",
        "toxic",
        "psychic",
        "double-team",
        "dream-eater",
        "flash",
        "rest",
        "substitute",
        "thief",
        "protect",
        "endure",
        "swagger",
        "attract",
        "sleep-talk",
        "return",
        "frustration",
        "hidden-power",
        "rain-dance",
        "sunny-day",
        "psych-up",
        "shadow-ball",
        "torment",
        "will-o-wisp",
        "facade",
        "taunt",
        "skill-swap",
        "snatch",
        "secret-power",
        "calm-mind",
        "natural-gift",
        "payback",
        "embargo",
        "fling",
        "dark-pulse",
        "trick-room",
        "captivate",
        "charge-beam"
    ],
    "firered-leafgreen": [
        "ice-beam",
        "blizzard",
        "toxic",
        "psychic",
        "double-team",
        "flash",
        "rest",
        "thief",
        "protect",
        "attract",
        "return",
        "frustration",
        "hidden-power",
        "rain-dance",
        "sunny-day",
        "shadow-ball",
        "torment",
        "facade",
        "taunt",
        "skill-swap",
        "snatch",
        "secret-power",
        "calm-mind"
    ],
    "emerald": [
        "ice-beam",
        "blizzard",
        "toxic",
        "psychic",
        "double-team",
        "flash",
        "rest",
        "thief",
        "protect",
        "attract",
        "return",
        "frustration",
        "hidden-power",
        "rain-dance",
        "sunny-day",
        "shadow-ball",
        "torment",
        "facade",
        "taunt",
        "skill-swap",
        "snatch",
        "secret-power",
        "calm-mind"
    ],
    "ruby-sapphire": [
        "ice-beam",
        "blizzard",
        "toxic",
        "psychic",
        "double-team",
        "flash",
        "rest",
        "thief",
        "protect",
        "attract",
        "return",
        "frustration",
        "hidden-power",
        "rain-dance",
        "sunny-day",
        "shadow-ball",
        "torment",
        "facade",
        "taunt",
        "skill-swap",
        "snatch",
        "secret-power",
        "calm-mind"
    ]
}