{
    "platinum": [
        "roar",
        "surf",
        "ice-beam",
        "blizzard",
        "hyper-beam",
        "strength",
        "earthquake",
        "toxic",
        "double-team",
        "waterfall",
        "rest",
        "rock-slide",
        "substitute",
        "protect",
        "endure",
        "swagger",
        "attract",
        "sleep-talk",
        "return",
        "frustration",
        "iron-tail",
        "hidden-power",
        "rain-dance",
        "rock-smash",
        "hail",
        "facade",
        "secret-power",
        "rock-tomb",
        "water-pulse",
        "brine",
        "natural-gift",
        "giga-impact",
        "avalanche",
        "captivate"
    ],
    "diamond-pearl": [
        "roar",
        "surf",
        "ice-beam",
        "blizzard",
        "hyper-beam",
        "strength",
        "earthquake",
        "toxic",
        "double-team",
        "waterfall",
        "rest",
        "rock-slide",
        "substitute",
        "protect",
        "endure",
        "swagger",
        "attract",
        "sleep-talk",
        "return",
        "frustration",
        "iron-tail",
        "hidden-power",
        "rain-dance",
        "rock-smash",
        "hail",
        "facade",
        "secret-power",
        "rock-tomb",
        "water-pulse",
        "brine",
        "natural-gift",
        "giga-impact",
        "avalanche",
        "captivate"
    ],
    "firered-leafgreen": [
        "roar",
        "surf",
        "ice-beam",
        "blizzard",
        "hyper-beam",
        "strength",
        "earthquake",
        "toxic",
        "double-team",
        "waterfall",
        "rest",
        "protect",
        "attract",
        "return",
        "frustration",
        "iron-tail",
        "hidden-power",
        "rain-dance",
        "rock-smash",
        "hail",
        "facade",
        "secret-power",
        "dive",
        "rock-tomb",
        "water-pulse"
    ],
    "emerald": [
        "roar",
        "surf",
        "ice-beam",
        "blizzard",
        "hyper-beam",
        "strength",
        "earthquake",
        "toxic",
        "double-team",
        "waterfall",
        "rest",
        "protect",
        "attract",
        "return",
        "frustration",
        "iron-tail",
        "hidden-power",
        "rain-dance",
        "rock-smash",
        "hail",
        "facade",
        "secret-power",
        "dive",
        "rock-tomb",
        "water-pulse"
    ],
    "ultra-sun-ultra-moon": [
        "roar",
        "surf",
        "ice-beam",
        "blizzard",
        "hyper-beam",
        "earthquake",
        "toxic",
        "double-team",
        "waterfall",
        "rest",
        "rock-slide",
        "substitute",
        "protect",
        "swagger",
        "attract",
        "sleep-talk",
        "return",
        "frustration",
        "hidden-power",
        "rain-dance",
        "hail",
        "facade",
        "rock-tomb",
        "giga-impact",
        "round",
        "echoed-voice",
        "bulldoze",
        "frost-breath",
        "confide"
    ],
    "sun-moon": [
        "roar",
        "surf",
        "ice-beam",
        "blizzard",
        "hyper-beam",
        "earthquake",
        "toxic",
        "double-team",
        "waterfall",
        "rest",
        "rock-slide",
        "substitute",
        "protect",
        "swagger",
        "attract",
        "sleep-talk",
        "return",
        "frustration",
        "hidden-power",
        "rain-dance",
        "hail",
        "facade",
        "rock-tomb",
        "giga-impact",
        "round",
        "echoed-voice",
        "bulldoze",
        "frost-breath",
        "confide"
    ],
    "omega-ruby-alpha-sapphire": [
        "roar",
        "surf",
        "ice-beam",
        "blizzard",
        "hyper-beam",
        "strength",
        "earthquake",
        "toxic",
        "double-team",
        "waterfall",
        "rest",
        "rock-slide",
        "substitute",
        "protect",
        "swagger",
        "attract",
        "sleep-talk",
        "return",
        "frustration",
        "hidden-power",
        "rain-dance",
        "rock-smash",
        "hail",
        "facade",
        "secret-power",
        "dive",
        "rock-tomb",
        "giga-impact",
        "round",
        "echoed-voice",
        "bulldoze",
        "frost-breath",
        "confide"
    ],
    "x-y": [
        "roar",
        "surf",
        "ice-beam",
        "blizzard",
        "hyper-beam",
        "strength",
        "earthquake",
        "toxic",
        "double-team",
        "waterfall",
        "rest",
        "rock-slide",
        "substitute",
        "protect",
        "swagger",
        "attract",
        "sleep-talk",
        "return",
        "frustration",
        "hidden-power",
        "rain-dance",
        "rock-smash",
        "hail",
        "facade",
        "rock-tomb",
        "giga-impact",
        "round",
        "echoed-voice",
        "bulldoze",
        "frost-breath",
        "confide"
    ],
    "black-2-white-2": [
        "roar",
        "surf",
        "ice-beam",
        "blizzard",
        "hyper-beam",
        "strength",
        "earthquake",
        "toxic",
        "double-team",
        "waterfall",
        "rest",
        "rock-slide",
        "substitute",
        "protect",
        "swagger",
        "attract",
        "return",
        "frustration",
        "hidden-power",
        "rain-dance",
        "rock-smash",
        "hail",
        "facade",
        "dive",
        "rock-tomb",
        "giga-impact",
        "round",
        "echoed-voice",
        "bulldoze",
        "frost-breath"
    ],
    "xd": [
        "roar",
        "surf",
        "ice-beam",
        "blizzard",
        "hyper-beam",
        "strength",
        "earthquake",
        "toxic",
        "double-team",
        "waterfall",
        "rest",
        "protect",
        "attract",
        "return",
        "frustration",
        "iron-tail",
        "hidden-power",
        "rain-dance",
        "rock-smash",
        "hail",
        "facade",
        "secret-power",
        "dive",
        "rock-tomb",
        "water-pulse"
    ],
    "colosseum": [
        "roar",
        "surf",
        "ice-beam",
        "blizzard",
        "hyper-beam",
        "strength",
        "earthquake",
        "toxic",
        "double-team",
        "waterfall",
        "rest",
        "protect",
        "attract",
        "return",
        "frustration",
        "iron-tail",
        "hidden-power",
        "rain-dance",
        "rock-smash",
        "hail",
        "facade",
        "secret-power",
        "dive",
        "rock-tomb",
        "water-pulse"
    ],
    "black-white": [
        "roar",
        "surf",
        "ice-beam",
        "blizzard",
        "hyper-beam",
        "strength",
        "earthquake",
        "toxic",
        "double-team",
        "waterfall",
        "rest",
        "rock-slide",
        "substitute",
        "protect",
        "swagger",
        "attract",
        "return",
        "frustration",
        "hidden-power",
        "rain-dance",
        "rock-smash",
        "hail",
        "facade",
        "dive",
        "rock-tomb",
        "giga-impact",
        "round",
        "echoed-voice",
        "bulldoze",
        "frost-breath"
    ],
    "heartgold-soulsilver": [
        "roar",
        "surf",
        "ice-beam",
        "blizzard",
        "hyper-beam",
        "strength",
        "earthquake",
        "toxic",
        "double-team",
        "waterfall",
        "rest",
        "rock-slide",
        "substitute",
        "protect",
        "endure",
        "swagger",
        "attract",
        "sleep-talk",
        "return",
        "frustration",
        "iron-tail",
        "hidden-power",
        "rain-dance",
        "rock-smash",
        "whirlpool",
        "hail",
        "facade",
        "secret-power",
        "rock-tomb",
        "water-pulse",
        "brine",
        "natural-gift",
        "giga-impact",
        "avalanche",
        "captivate"
    ],
    "ruby-sapphire": [
        "roar",
        "surf",
        "ice-beam",
        "blizzard",
        "hyper-beam",
        "strength",
        "earthquake",
        "toxic",
        "double-team",
        "waterfall",
        "rest",
        "protect",
        "attract",
        "return",
        "frustration",
        "iron-tail",
        "hidden-power",
        "rain-dance",
        "rock-smash",
        "hail",
        "facade",
        "secret-power",
        "dive",
        "rock-tomb",
        "water-pulse"
    ]
}