{
    "omega-ruby-alpha-sapphire": [
        "cut",
        "fly",
        "hyper-beam",
        "thunderbolt",
        "thunder-wave",
        "thunder",
        "toxic",
        "psychic",
        "double-team",
        "dream-eater",
        "flash",
        "explosion",
        "rest",
        "substitute",
        "thief",
        "protect",
        "swagger",
        "attract",
        "sleep-talk",
        "return",
        "frustration",
        "hidden-power",
        "rain-dance",
        "sunny-day",
        "psych-up",
        "shadow-ball",
        "will-o-wisp",
        "facade",
        "secret-power",
        "calm-mind",
        "gyro-ball",
        "payback",
        "embargo",
        "giga-impact",
        "charge-beam",
        "round",
        "acrobatics",
        "confide"
    ],
    "x-y": [
        "cut",
        "fly",
        "hyper-beam",
        "thunderbolt",
        "thunder-wave",
        "thunder",
        "toxic",
        "psychic",
        "double-team",
        "dream-eater",
        "flash",
        "explosion",
        "rest",
        "substitute",
        "thief",
        "protect",
        "swagger",
        "attract",
        "sleep-talk",
        "return",
        "frustration",
        "hidden-power",
        "rain-dance",
        "sunny-day",
        "psych-up",
        "shadow-ball",
        "will-o-wisp",
        "facade",
        "calm-mind",
        "gyro-ball",
        "payback",
        "embargo",
        "giga-impact",
        "charge-beam",
        "round",
        "acrobatics",
        "confide"
    ],
    "black-2-white-2": [
        "cut",
        "fly",
        "hyper-beam",
        "thunderbolt",
        "thunder-wave",
        "thunder",
        "toxic",
        "psychic",
        "double-team",
        "dream-eater",
        "flash",
        "explosion",
        "rest",
        "substitute",
        "thief",
        "protect",
        "swagger",
        "attract",
        "return",
        "frustration",
        "hidden-power",
        "rain-dance",
        "sunny-day",
        "psych-up",
        "shadow-ball",
        "will-o-wisp",
        "facade",
        "calm-mind",
        "gyro-ball",
        "payback",
        "embargo",
        "giga-impact",
        "charge-beam",
        "telekinesis",
        "round",
        "acrobatics"
    ],
    "black-white": [
        "cut",
        "fly",
        "hyper-beam",
        "thunderbolt",
        "thunder-wave",
        "thunder",
        "toxic",
        "psychic",
        "double-team",
        "dream-eater",
        "flash",
        "explosion",
        "rest",
        "substitute",
        "thief",
        "protect",
        "swagger",
        "attract",
        "return",
        "frustration",
        "hidden-power",
        "rain-dance",
        "sunny-day",
        "psych-up",
        "shadow-ball",
        "will-o-wisp",
        "facade",
        "calm-mind",
        "gyro-ball",
        "payback",
        "embargo",
        "giga-impact",
        "charge-beam",
        "telekinesis",
        "round",
        "acrobatics"
    ],
    "heartgold-soulsilver": [
        "cut",
        "fly",
        "hyper-beam",
        "thunderbolt",
        "thunder-wave",
        "thunder",
        "toxic",
        "psychic",
        "double-team",
        "dream-eater",
        "flash",
        "explosion",
        "rest",
        "substitute",
        "thief",
        "protect",
        "endure",
        "swagger",
        "attract",
        "sleep-talk",
        "return",
        "frustration",
        "hidden-power",
        "rain-dance",
        "sunny-day",
        "psych-up",
        "shadow-ball",
        "will-o-wisp",
        "facade",
        "recycle",
        "skill-swap",
        "secret-power",
        "silver-wind",
        "calm-mind",
        "shock-wave",
        "gyro-ball",
        "natural-gift",
        "payback",
        "embargo",
        "giga-impact",
        "captivate",
        "charge-beam"
    ],
    "platinum": [
        "cut",
        "fly",
        "hyper-beam",
        "thunderbolt",
        "thunder-wave",
        "thunder",
        "toxic",
        "psychic",
        "double-team",
        "dream-eater",
        "flash",
        "explosion",
        "rest",
        "substitute",
        "thief",
        "protect",
        "endure",
        "swagger",
        "attract",
        "sleep-talk",
        "return",
        "frustration",
        "hidden-power",
        "rain-dance",
        "sunny-day",
        "psych-up",
        "shadow-ball",
        "will-o-wisp",
        "facade",
        "recycle",
        "skill-swap",
        "secret-power",
        "silver-wind",
        "calm-mind",
        "shock-wave",
        "gyro-ball",
        "natural-gift",
        "payback",
        "embargo",
        "giga-impact",
        "defog",
        "captivate",
        "charge-beam"
    ],
    "diamond-pearl": [
        "cut",
        "fly",
        "hyper-beam",
        "thunderbolt",
        "thunder-wave",
        "thunder",
        "toxic",
        "psychic",
        "double-team",
        "dream-eater",
        "flash",
        "explosion",
        "rest",
        "substitute",
        "thief",
        "protect",
        "endure",
        "swagger",
        "attract",
        "sleep-talk",
        "return",
        "frustration",
        "hidden-power",
        "rain-dance",
        "sunny-day",
        "psych-up",
        "shadow-ball",
        "will-o-wisp",
        "facade",
        "recycle",
        "skill-swap",
        "secret-power",
        "silver-wind",
        "calm-mind",
        "shock-wave",
        "gyro-ball",
        "natural-gift",
        "payback",
        "embargo",
        "giga-impact",
        "defog",
        "captivate",
        "charge-beam"
    ],
    "ultra-sun-ultra-moon": [
        "fly",
        "hyper-beam",
        "thunderbolt",
        "thunder-wave",
        "thunder",
        "toxic",
        "psychic",
        "double-team",
        "dream-eater",
        "explosion",
        "rest",
        "substitute",
        "thief",
        "protect",
        "swagger",
        "attract",
        "sleep-talk",
        "return",
        "frustration",
        "hidden-power",
        "rain-dance",
        "sunny-day",
        "psych-up",
        "shadow-ball",
        "will-o-wisp",
        "facade",
        "calm-mind",
        "gyro-ball",
        "payback",
        "embargo",
        "giga-impact",
        "charge-beam",
        "round",
        "acrobatics",
        "confide"
    ],
    "sun-moon": [
        "fly",
        "hyper-beam",
        "thunderbolt",
        "thunder-wave",
        "thunder",
        "toxic",
        "psychic",
        "double-team",
        "dream-eater",
        "explosion",
        "rest",
        "substitute",
        "thief",
        "protect",
        "swagger",
        "attract",
        "sleep-talk",
        "return",
        "frustration",
        "hidden-power",
        "rain-dance",
        "sunny-day",
        "psych-up",
        "shadow-ball",
        "will-o-wisp",
        "facade",
        "calm-mind",
        "gyro-ball",
        "payback",
        "embargo",
        "giga-impact",
        "charge-beam",
        "round",
        "acrobatics",
        "confide"
    ]
}