{
    "ultra-sun-ultra-moon": [
        "flamethrower",
        "surf",
        "ice-beam",
        "blizzard",
        "hyper-beam",
        "solar-beam",
        "thunderbolt",
        "thunder-wave",
        "thunder",
        "toxic",
        "psychic",
        "double-team",
        "light-screen",
        "reflect",
        "fire-blast",
        "dream-eater",
        "rest",
        "substitute",
        "protect",
        "swagger",
        "attract",
        "sleep-talk",
        "return",
        "frustration",
        "safeguard",
        "hidden-power",
        "rain-dance",
        "sunny-day",
        "psych-up",
        "shadow-ball",
        "facade",
        "calm-mind",
        "fling",
        "trick-room",
        "grass-knot",
        "charge-beam",
        "psyshock",
        "round",
        "echoed-voice",
        "work-up",
        "wild-charge",
        "confide",
        "dazzling-gleam"
    ],
    "sun-moon": [
        "flamethrower",
        "surf",
        "ice-beam",
        "blizzard",
        "hyper-beam",
        "solar-beam",
        "thunderbolt",
        "thunder-wave",
        "thunder",
        "toxic",
        "psychic",
        "double-team",
        "light-screen",
        "reflect",
        "fire-blast",
        "dream-eater",
        "rest",
        "substitute",
        "protect",
        "swagger",
        "attract",
        "sleep-talk",
        "return",
        "frustration",
        "safeguard",
        "hidden-power",
        "rain-dance",
        "sunny-day",
        "psych-up",
        "shadow-ball",
        "facade",
        "calm-mind",
        "fling",
        "trick-room",
        "grass-knot",
        "charge-beam",
        "psyshock",
        "round",
        "echoed-voice",
        "work-up",
        "wild-charge",
        "confide",
        "dazzling-gleam"
    ],
    "omega-ruby-alpha-sapphire": [
        "flamethrower",
        "surf",
        "ice-beam",
        "blizzard",
        "hyper-beam",
        "solar-beam",
        "thunderbolt",
        "thunder-wave",
        "thunder",
        "dig",
        "toxic",
        "psychic",
        "double-team",
        "light-screen",
        "reflect",
        "fire-blast",
        "dream-eater",
        "flash",
        "rest",
        "substitute",
        "protect",
        "swagger",
        "attract",
        "sleep-talk",
        "return",
        "frustration",
        "safeguard",
        "hidden-power",
        "rain-dance",
        "sunny-day",
        "psych-up",
        "shadow-ball",
        "facade",
        "secret-power",
        "calm-mind",
        "fling",
        "trick-room",
        "grass-knot",
        "charge-beam",
        "psyshock",
        "round",
        "echoed-voice",
        "incinerate",
        "retaliate",
        "wild-charge",
        "confide",
        "dazzling-gleam",
        "power-up-punch"
    ],
    "x-y": [
        "flamethrower",
        "surf",
        "ice-beam",
        "blizzard",
        "hyper-beam",
        "solar-beam",
        "thunderbolt",
        "thunder-wave",
        "thunder",
        "dig",
        "toxic",
        "psychic",
        "double-team",
        "light-screen",
        "reflect",
        "fire-blast",
        "dream-eater",
        "flash",
        "rest",
        "substitute",
        "protect",
        "swagger",
        "attract",
        "sleep-talk",
        "return",
        "frustration",
        "safeguard",
        "hidden-power",
        "rain-dance",
        "sunny-day",
        "psych-up",
        "shadow-ball",
        "facade",
        "calm-mind",
        "fling",
        "trick-room",
        "grass-knot",
        "charge-beam",
        "psyshock",
        "round",
        "echoed-voice",
        "incinerate",
        "retaliate",
        "wild-charge",
        "confide",
        "dazzling-gleam",
        "power-up-punch"
    ],
    "black-2-white-2": [
        "flamethrower",
        "surf",
        "ice-beam",
        "blizzard",
        "hyper-beam",
        "solar-beam",
        "thunderbolt",
        "thunder-wave",
        "thunder",
        "dig",
        "toxic",
        "psychic",
        "double-team",
        "light-screen",
        "reflect",
        "fire-blast",
        "dream-eater",
        "flash",
        "rest",
        "substitute",
        "protect",
        "swagger",
        "attract",
        "return",
        "frustration",
        "safeguard",
        "hidden-power",
        "rain-dance",
        "sunny-day",
        "psych-up",
        "shadow-ball",
        "facade",
        "calm-mind",
        "fling",
        "trick-room",
        "grass-knot",
        "charge-beam",
        "psyshock",
        "telekinesis",
        "round",
        "echoed-voice",
        "incinerate",
        "retaliate",
        "work-up",
        "wild-charge"
    ],
    "black-white": [
        "flamethrower",
        "surf",
        "ice-beam",
        "blizzard",
        "hyper-beam",
        "solar-beam",
        "thunderbolt",
        "thunder-wave",
        "thunder",
        "dig",
        "toxic",
        "psychic",
        "double-team",
        "light-screen",
        "reflect",
        "fire-blast",
        "dream-eater",
        "flash",
        "rest",
        "substitute",
        "protect",
        "swagger",
        "attract",
        "return",
        "frustration",
        "safeguard",
        "hidden-power",
        "rain-dance",
        "sunny-day",
        "psych-up",
        "shadow-ball",
        "facade",
        "calm-mind",
        "fling",
        "trick-room",
        "grass-knot",
        "charge-beam",
        "psyshock",
        "telekinesis",
        "round",
        "echoed-voice",
        "incinerate",
        "retaliate",
        "work-up",
        "wild-charge"
    ]
}