{
    "ultra-sun-ultra-moon": [
        "toxic",
        "double-team",
        "explosion",
        "rest",
        "substitute",
        "thief",
        "protect",
        "sludge-bomb",
        "swagger",
        "attract",
        "sleep-talk",
        "return",
        "frustration",
        "hidden-power",
        "rain-dance",
        "sunny-day",
        "facade",
        "payback",
        "dark-pulse",
        "venoshock",
        "sludge-wave",
        "round",
        "confide",
        "infestation"
    ],
    "sun-moon": [
        "toxic",
        "double-team",
        "explosion",
        "rest",
        "substitute",
        "thief",
        "protect",
        "sludge-bomb",
        "swagger",
        "attract",
        "sleep-talk",
        "return",
        "frustration",
        "hidden-power",
        "rain-dance",
        "sunny-day",
        "facade",
        "payback",
        "dark-pulse",
        "venoshock",
        "sludge-wave",
        "round",
        "confide",
        "infestation"
    ],
    "omega-ruby-alpha-sapphire": [
        "toxic",
        "double-team",
        "explosion",
        "rest",
        "substitute",
        "thief",
        "protect",
        "sludge-bomb",
        "swagger",
        "attract",
        "sleep-talk",
        "return",
        "frustration",
        "hidden-power",
        "rain-dance",
        "sunny-day",
        "facade",
        "secret-power",
        "payback",
        "dark-pulse",
        "venoshock",
        "sludge-wave",
        "round",
        "confide",
        "infestation"
    ],
    "x-y": [
        "toxic",
        "double-team",
        "explosion",
        "rest",
        "substitute",
        "thief",
        "protect",
        "sludge-bomb",
        "swagger",
        "attract",
        "sleep-talk",
        "return",
        "frustration",
        "hidden-power",
        "rain-dance",
        "sunny-day",
        "facade",
        "payback",
        "dark-pulse",
        "venoshock",
        "sludge-wave",
        "round",
        "confide",
        "infestation"
    ],
    "black-2-white-2": [
        "toxic",
        "double-team",
        "explosion",
        "rest",
        "substitute",
        "thief",
        "protect",
        "sludge-bomb",
        "swagger",
        "attract",
        "return",
        "frustration",
        "hidden-power",
        "rain-dance",
        "sunny-day",
        "facade",
        "payback",
        "venoshock",
        "sludge-wave",
        "round"
    ],
    "black-white": [
        "toxic",
        "double-team",
        "explosion",
        "rest",
        "substitute",
        "thief",
        "protect",
        "sludge-bomb",
        "swagger",
        "attract",
        "return",
        "frustration",
        "hidden-power",
        "rain-dance",
        "sunny-day",
        "facade",
        "payback",
        "venoshock",
        "sludge-wave",
        "round"
    ]
}